setup.py
jmz/__init__.py
jmz/tools/__init__.py
jmz/tools/crypto.js
jmz/tools/crypto.py
jmz_api.egg-info/PKG-INFO
jmz_api.egg-info/SOURCES.txt
jmz_api.egg-info/dependency_links.txt
jmz_api.egg-info/requires.txt
jmz_api.egg-info/top_level.txt