Metadata-Version: 2.1
Name: jmz_api
Version: 0.0.8
Summary: 这是作者开发日常写的一些工具库和平台爬虫API工具集合
Author: jinmingzhou
Author-email: 17816765317@163.com
Requires-Dist: PyExecJS2
